gatree/__init__.py
gatree/ga/__init__.py
gatree/ga/crossover.py
gatree/ga/mutation.py
gatree/ga/selection.py
gatree/gatree.py
gatree/methods/__init__.py
gatree/methods/gatreeclassifier.py
gatree/methods/gatreeclustering.py
gatree/tree/__init__.py
gatree/tree/node.py
gatree-0.2.0.dist-info/LICENSE
gatree-0.2.0.dist-info/METADATA
gatree-0.2.0.dist-info/WHEEL
gatree-0.2.0.dist-info/RECORD
