Metadata-Version: 2.1
Name: gatree
Version: 0.2.0
Summary: 
Author: Tadej Lahovnik
Author-email: tadej.lahovnik@student.um.si
Requires-Python: >=3.9,<4.0
Classifier: Programming Language :: Python :: 3
Classifier: Programming Language :: Python :: 3.9
Classifier: Programming Language :: Python :: 3.10
Classifier: Programming Language :: Python :: 3.11
Classifier: Programming Language :: Python :: 3.12
Provides-Extra: docs
Requires-Dist: numpy (>=1.26.0,<2.0.0)
Requires-Dist: pandas (>=2.1.1,<3.0.0)
Requires-Dist: scikit-learn (>=1.3.0,<2.0.0)
Requires-Dist: scipy (>=1.11.2,<2.0.0)
Requires-Dist: sphinx-rtd-theme[docs] (>=1.0.0,<2.0.0) ; extra == "docs"
Requires-Dist: sphinx[docs] (>=5.0,<6.0) ; extra == "docs"
